pantsbuild.pants.contrib.googlejavaformat-1.28.0-py3.6-nspkg.pth
pants/contrib/googlejavaformat/__init__.py
pants/contrib/googlejavaformat/googlejavaformat.py
pants/contrib/googlejavaformat/register.py
pants/contrib/googlejavaformat/subsystem.py
pantsbuild.pants.contrib.googlejavaformat-1.28.0.dist-info/METADATA
pantsbuild.pants.contrib.googlejavaformat-1.28.0.dist-info/WHEEL
pantsbuild.pants.contrib.googlejavaformat-1.28.0.dist-info/entry_points.txt
pantsbuild.pants.contrib.googlejavaformat-1.28.0.dist-info/namespace_packages.txt
pantsbuild.pants.contrib.googlejavaformat-1.28.0.dist-info/top_level.txt
pantsbuild.pants.contrib.googlejavaformat-1.28.0.dist-info/zip-safe
pantsbuild.pants.contrib.googlejavaformat-1.28.0.dist-info/RECORD
